pyvarium/__init__.py
pyvarium/cli/__init__.py
pyvarium/cli/add.py
pyvarium/cli/config.py
pyvarium/cli/install.py
pyvarium/cli/modulegen.py
pyvarium/cli/new.py
pyvarium/cli/sync.py
pyvarium/cli/verify.py
pyvarium/config.py
pyvarium/installers/__init__.py
pyvarium/installers/base.py
pyvarium/installers/pipenv.py
pyvarium/installers/spack.py
pyvarium/settings.toml
pyvarium/util/__init__.py
pyvarium/util/python_venv.py
pyvarium-0.2.0.dist-info/entry_points.txt
pyvarium-0.2.0.dist-info/WHEEL
pyvarium-0.2.0.dist-info/METADATA
pyvarium-0.2.0.dist-info/RECORD
